setup.cfg
setup.py
fi_aa295.egg-info/PKG-INFO
fi_aa295.egg-info/SOURCES.txt
fi_aa295.egg-info/dependency_links.txt
fi_aa295.egg-info/not-zip-safe
fi_aa295.egg-info/top_level.txt
fi_aa295/circle/__init__.py
fi_aa295/circle/code.py
fi_aa295/square/__init__.py
fi_aa295/square/code.py
fi_aa295/triangle/__init__.py
fi_aa295/triangle/code.py