Metadata-Version: 2.1
Name: fi-aa295
Version: 0.0
Summary: circle, triangle, square
Author-email: sachaglushchenko08@gmail.com
